README.md
setup.py
pytodd/__init__.py
pytodd/download.py
pytodd/gdrive.py
pytodd/settings.py
pytodd.egg-info/PKG-INFO
pytodd.egg-info/SOURCES.txt
pytodd.egg-info/dependency_links.txt
pytodd.egg-info/requires.txt
pytodd.egg-info/top_level.txt