Metadata-Version: 1.1
Name: pytodd
Version: 0.1.3
Summary: Python port of todd project for Google Drive IO.
Home-page: https://github.com/siddhantkushwaha/pytodd
Author: Siddhant Kushwaha
Author-email: k16.siddhant@gmail.com
License: MIT
Download-URL: https://github.com/siddhantkushwaha/pytodd/archive/0.1.3.tar.gz
Keywords: GOOGLE DRIVE,STORAGE,DOWNLOAD
Platform: UNKNOWN
Classifier: Development Status :: 3 - Alpha
Classifier: Intended Audience :: Developers
Classifier: Topic :: Software Development :: Build Tools
Classifier: License :: OSI Approved :: MIT License
Classifier: Programming Language :: Python :: 3.6
Classifier: Programming Language :: Python :: 3.7
Classifier: Programming Language :: Python :: 3.8
